{
  "$schema": "http://json-schema.org/draft-07/schema#",
  "$id": "http://frontend.ruhmesmeile.com/base/atoms/button.schema.json",
  "title": "Button",
  "description": "Component to display links and call-to-actions",
  "type": "object",
  "definitions": {
    "button": {
      "type": "object",
      "properties": {
        "label": {
          "type": "string",
          "title": "Label",
          "description": "Text used on button",
          "default": "Lorem Ipsum"
        },
        "variant": {
          "type": "string",
          "enum": [
            "solid",
            "solid-inverted",
            "clear",
            "clear-inverted",
            "outline",
            "outline-inverted"
          ],
          "title": "Button Style",
          "description": "Choose one of the styles from the list",
          "default": "solid"
        },
        "size": {
          "type": "string",
          "enum": ["small", "medium", "large"],
          "default": "medium",
          "title": "Button Size",
          "description": "Choose a size between small, medium and large"
        },
        "className": {
          "type": "string",
          "title": "Additional Classes",
          "description": "Add additional css classes that should be applied to the button"
        },
        "icon": {
          "$ref": "http://frontend.ruhmesmeile.com/base/atoms/icon.definitions.json"
        },
        "iconBefore": {
          "type": "boolean",
          "title": "Icon before button",
          "description": "Display icon before the button text",
          "default": false
        },
        "iconAfter": {
          "type": "boolean",
          "title": "Icon after button",
          "description": "Display icon after the button text",
          "default": false
        },
        "dataComponent": {
          "type": "string",
          "title": "`data-component` attribute",
          "description": "Overwrite the data-component to use for rendering"
        },
        "fillAnimation": {
          "type": "boolean",
          "default": false,
          "title": "Fill Animation",
          "description": "Add fill animation on hover"
        },
        "iconAnimation": {
          "type": "boolean",
          "default": false,
          "title": "Icon Animation",
          "description": "Add icon animation on hover"
        }
      },
      "required": ["label", "variant", "size"],
      "additionalProperties": false
    }
  },
  "allOf": [
    {
      "$ref": "#/definitions/button"
    },
    {
      "type": "object",
      "properties": {
        "type": {
          "type": "string",
          "enum": ["button", "submit", "reset"],
          "default": "button",
          "title": "`type` attribute",
          "description": "Select the type attribute for the button"
        },
        "value": {
          "type": "string",
          "title": "`value` attribute",
          "description": "Define a value attribute for the button"
        },
        "name": {
          "type": "string",
          "title": "`name` attribute",
          "description": "Define a name attribute for the button"
        },
        "disabled": {
          "type": "boolean",
          "default": false,
          "title": "`disabled` attribute",
          "description": "Set the disabled attribute for the button"
        }
      },
      "required": ["type"],
      "additionalProperties": false
    }
  ]
}
